CoreSharedLibs/__init__.py
CoreSharedLibs/app.py
CoreSharedLibs/csl.py
BTCoreSharedLibs-0.0.4.dist-info/LICENSE
BTCoreSharedLibs-0.0.4.dist-info/METADATA
BTCoreSharedLibs-0.0.4.dist-info/WHEEL
BTCoreSharedLibs-0.0.4.dist-info/entry_points.txt
BTCoreSharedLibs-0.0.4.dist-info/top_level.txt
BTCoreSharedLibs-0.0.4.dist-info/RECORD
